bq/__init__.py
bq/app.py
bq/config.py
bq/constants.py
bq/events.py
bq/utils.py
bq/cmds/__init__.py
bq/cmds/cli.py
bq/cmds/create_tables.py
bq/cmds/environment.py
bq/cmds/main.py
bq/cmds/process.py
bq/cmds/submit.py
bq/cmds/utils.py
bq/db/__init__.py
bq/db/base.py
bq/db/session.py
bq/models/__init__.py
bq/models/event.py
bq/models/helpers.py
bq/models/task.py
bq/models/worker.py
bq/processors/__init__.py
bq/processors/processor.py
bq/processors/registry.py
bq/processors/retry_policies.py
bq/services/__init__.py
bq/services/dispatch.py
bq/services/worker.py
beanqueue-1.1.9.dist-info/METADATA
beanqueue-1.1.9.dist-info/WHEEL
beanqueue-1.1.9.dist-info/entry_points.txt
beanqueue-1.1.9.dist-info/licenses/LICENSE
beanqueue-1.1.9.dist-info/RECORD
