Metadata-Version: 2.4
Name: beanqueue
Version: 1.1.9
Summary: BeanQueue or BQ for short, PostgreSQL SKIP LOCK and SQLAlchemy based worker queue library
Author-email: Fang-Pen Lin <fangpen@launchplatform.com>
License-Expression: MIT
License-File: LICENSE
Requires-Python: ~=3.11
Requires-Dist: blinker<2,>=1.8.2
Requires-Dist: click<9,>=8.1.7
Requires-Dist: pydantic-settings<3,>=2.2.1
Requires-Dist: rich<14,>=13.7.1
Requires-Dist: sqlalchemy<3,>=2.0.30
Requires-Dist: venusian<4,>=3.1.0
